{
  "version": 4,
  "savedAt": "2026-04-30T12:44:35.962Z",
  "cases": [
    {
      "id": "case_n01",
      "caseGroup": "G_n01",
      "include": true,
      "month": "9月",
      "species": "スズメバチ",
      "location": "屋外",
      "workType": "巣3つ／高所作業（残蜂捕獲）",
      "price": "77,000円",
      "duration": "",
      "area": "",
      "notes": "case_n11と同案件C11の残蜂処理写真",
      "visual": "黒い粘着シート2枚をアスファルト上に。捕獲された蜂多数",
      "rawText": "（近接テキスト無し）",
      "origin": "image1.jpeg / M1:O10",
      "imagePath": "docs/images/case_n01.jpg"
    },
    {
      "id": "case_n02",
      "caseGroup": "G_n02",
      "include": true,
      "month": "9月",
      "species": "オオスズメバチ",
      "location": "地中",
      "workType": "地中作業",
      "price": "66,000円",
      "duration": "",
      "area": "",
      "notes": "原文はオオスズメバチ地中66,000円。case_n13/n14の地中案件と同C12の可能性",
      "visual": "コンクリブロックの隅。明確な蜂・巣は確認しづらい",
      "rawText": "高所作業 / 22,000円 / 9月 / オオスズメバチ / 地中 / 66,000円",
      "origin": "image2.jpeg / F36:I46",
      "imagePath": "docs/images/case_n02.jpg"
    },
    {
      "id": "case_n03",
      "caseGroup": "C5a",
      "include": true,
      "month": "6月",
      "species": "スズメバチ",
      "location": "（要確認）",
      "workType": "高所作業",
      "price": "38,500円",
      "duration": "",
      "area": "",
      "notes": "Excel原文准拠。画像は床下風景に見える。要クライアント確認",
      "visual": "床下/暗所の風景（コンクリブロック壁、土の床）",
      "rawText": "6月 / スズメバチ / 高所作業 / 38,500円",
      "origin": "image3.jpeg / B1:E8",
      "imagePath": "docs/images/case_n03.jpg"
    },
    {
      "id": "case_n04",
      "caseGroup": "C5a",
      "include": true,
      "month": "6月",
      "species": "スズメバチ",
      "location": "（要確認）",
      "workType": "高所作業",
      "price": "38,500円",
      "duration": "",
      "area": "",
      "notes": "case_n03とPAIR",
      "visual": "暗所の大型蜂の巣（黄褐色、構造物の中）",
      "rawText": "（近接テキスト無し）",
      "origin": "image4.jpeg / E1:H8",
      "imagePath": "docs/images/case_n04.jpg"
    },
    {
      "id": "case_n05",
      "caseGroup": "C5b",
      "include": true,
      "month": "6月",
      "species": "スズメバチ",
      "location": "庭木",
      "workType": "高所作業",
      "price": "38,500円",
      "duration": "",
      "area": "",
      "notes": "原文「高所作業/38,500円」を採用。「刺され跡」はn12のテキスト混入",
      "visual": "庭木の枝の中に灰色の小さなアシナガバチ巣",
      "rawText": "高所作業 / 38,500円 / スズメバチに刺された跡",
      "origin": "image5.jpeg / B17:D26",
      "imagePath": "docs/images/case_n05.jpg"
    },
    {
      "id": "case_n06",
      "caseGroup": "G_n02",
      "include": true,
      "month": "9月",
      "species": "オオスズメバチ",
      "location": "地中（撤去後）",
      "workType": "解体写真",
      "price": "66,000円",
      "duration": "",
      "area": "",
      "notes": "case_n02と同案件C12の解体写真",
      "visual": "スズメバチ巣の解体写真（内部、オレンジ色のスズメバチ多数）",
      "rawText": "（近接テキスト無し）",
      "origin": "image6.jpeg / I36:K46",
      "imagePath": "docs/images/case_n06.jpg"
    },
    {
      "id": "case_n07",
      "caseGroup": "C8",
      "include": true,
      "month": "5月",
      "species": "スズメバチ",
      "location": "床下",
      "workType": "床下作業",
      "price": "44,000円",
      "duration": "",
      "area": "",
      "notes": "原文「床下/44,000円」を採用",
      "visual": "古民家の瓦屋根、軒下に小さな巣",
      "rawText": "床下 / 44,000円 / 5月 / 5月 / アシナガバチ / スズメバチ / 追加費用なし / 追加費用無し / 11,000円 / 22,000円",
      "origin": "image7.jpeg / B9:E16",
      "imagePath": "docs/images/case_n07.jpg"
    },
    {
      "id": "case_n08",
      "caseGroup": "C8",
      "include": true,
      "month": "5月",
      "species": "スズメバチ",
      "location": "（撤去後）",
      "workType": "追加費用無し",
      "price": "22,000円",
      "duration": "",
      "area": "",
      "notes": "Excel原文准拠",
      "visual": "撤去済み茶色球形スズメバチ巣（トレーに）",
      "rawText": "5月 / スズメバチ / 追加費用無し / 22,000円",
      "origin": "image8.jpeg / E8:H16",
      "imagePath": "docs/images/case_n08.jpg"
    },
    {
      "id": "case_n09",
      "caseGroup": "C13",
      "include": true,
      "month": "9月",
      "species": "スズメバチ",
      "location": "（撤去後）",
      "workType": "高所作業",
      "price": "",
      "duration": "",
      "area": "",
      "notes": "Excel原文准拠。料金欠落",
      "visual": "撤去済みスズメバチ巣（卵が見える）+ トング",
      "rawText": "9月 / スズメバチ / 高所作業",
      "origin": "image9.jpeg / U21:W30",
      "imagePath": "docs/images/case_n09.jpg"
    },
    {
      "id": "case_n10",
      "caseGroup": "C8b",
      "include": true,
      "month": "7月",
      "species": "スズメバチ",
      "location": "（撤去後）",
      "workType": "軽作業",
      "price": "36,300円",
      "duration": "",
      "area": "",
      "notes": "case_n25とPAIR",
      "visual": "複数の大型撤去済み巣（集合写真）",
      "rawText": "7月 / スズメバチ / 軽作業 / 36,300円",
      "origin": "image10.jpeg / R1:T10",
      "imagePath": "docs/images/case_n10.jpg"
    },
    {
      "id": "case_n11",
      "caseGroup": "G_n01",
      "include": true,
      "month": "9月",
      "species": "スズメバチ",
      "location": "（撤去後）",
      "workType": "巣3つ／高所作業",
      "price": "77,000円",
      "duration": "",
      "area": "",
      "notes": "case_n01とPAIR",
      "visual": "撤去済みの巣（複数の塊）",
      "rawText": "9月 / スズメバチ / 巣3つ / 高所作業",
      "origin": "image11.jpeg / K1:M10",
      "imagePath": "docs/images/case_n11.jpg"
    },
    {
      "id": "case_n12",
      "caseGroup": "C4",
      "include": true,
      "month": "5月",
      "species": "スズメバチ",
      "location": "",
      "workType": "刺され跡（注意喚起）",
      "price": "27,500円",
      "duration": "",
      "area": "",
      "notes": "刺され跡。施工事例ではなく注意喚起コンテンツ用に推奨",
      "visual": "人の腰のスズメバチ刺され跡（赤い炎症）",
      "rawText": "5月 / スズメバチ / 高所作業 / 27,500円",
      "origin": "image12.jpeg / B28:D37",
      "imagePath": "docs/images/case_n12.jpg"
    },
    {
      "id": "case_n13",
      "caseGroup": "C12",
      "include": true,
      "month": "9月",
      "species": "オオスズメバチ",
      "location": "地中（木の根元）",
      "workType": "地中作業",
      "price": "66,000円",
      "duration": "",
      "area": "",
      "notes": "case_n14とPAIR、case_n02/n06と同案件C12",
      "visual": "木の根元の地中にスズメバチ巣（むき出し）",
      "rawText": "（近接テキスト無し）",
      "origin": "image13.jpeg / G48:I57",
      "imagePath": "docs/images/case_n13.jpg"
    },
    {
      "id": "case_n14",
      "caseGroup": "C12",
      "include": true,
      "month": "9月",
      "species": "オオスズメバチ",
      "location": "地中（残蜂捕獲）",
      "workType": "地中作業／粘着シート",
      "price": "66,000円",
      "duration": "",
      "area": "",
      "notes": "case_n13とPAIR",
      "visual": "木の根元に粘着シート、大量のオオスズメバチ捕獲",
      "rawText": "（近接テキスト無し）",
      "origin": "image14.jpeg / I48:K58",
      "imagePath": "docs/images/case_n14.jpg"
    },
    {
      "id": "case_n15",
      "caseGroup": "C7b",
      "include": true,
      "month": "7月",
      "species": "スズメバチ",
      "location": "樹上",
      "workType": "高所作業",
      "price": "44,000円",
      "duration": "",
      "area": "",
      "notes": "case_n16とPAIR",
      "visual": "樹上の小さな巣（高所、枝の中）",
      "rawText": "（近接テキスト無し）",
      "origin": "image15.jpeg / Q33:S42",
      "imagePath": "docs/images/case_n15.jpg"
    },
    {
      "id": "case_n16",
      "caseGroup": "C7b",
      "include": true,
      "month": "7月",
      "species": "スズメバチ",
      "location": "樹上（道路際）",
      "workType": "高所作業",
      "price": "44,000円",
      "duration": "",
      "area": "",
      "notes": "case_n15とPAIR",
      "visual": "道路際の植栽の中に巣、駐車場のコーン置き",
      "rawText": "7月 / スズメバチ / 高所作業 / 44,000円",
      "origin": "image16.jpeg / N33:P42",
      "imagePath": "docs/images/case_n16.jpg"
    },
    {
      "id": "case_n17",
      "caseGroup": "C5c",
      "include": true,
      "month": "6月",
      "species": "スズメバチ",
      "location": "庭の植え込み",
      "workType": "高所作業",
      "price": "38,500円",
      "duration": "",
      "area": "",
      "notes": "Excel原文准拠。SOLO",
      "visual": "庭の植え込みの根元に大きな球形のスズメバチ巣",
      "rawText": "6月 / スズメバチ / 高所作業 / 38,500円",
      "origin": "image17.jpeg / R11:U19",
      "imagePath": "docs/images/case_n17.jpg"
    },
    {
      "id": "case_n18",
      "caseGroup": "G_n18",
      "include": true,
      "month": "8月",
      "species": "スズメバチ",
      "location": "屋根裏",
      "workType": "屋根裏／高所作業",
      "price": "55,000円",
      "duration": "",
      "area": "",
      "notes": "Excel原文＋関連事例から55,000円推定",
      "visual": "アスファルトに3つの撤去済みスズメバチ巣（大型）",
      "rawText": "8月 / スズメバチ / 屋根裏 / 高所作業",
      "origin": "image18.jpeg / K12:M19",
      "imagePath": "docs/images/case_n18.jpg"
    },
    {
      "id": "case_n19",
      "caseGroup": "G_n20",
      "include": true,
      "month": "9月",
      "species": "スズメバチ",
      "location": "（換気口）",
      "workType": "高所作業／捕獲",
      "price": "36,300円",
      "duration": "",
      "area": "",
      "notes": "case_n21と同案件と推定",
      "visual": "換気口の格子に大量のスズメバチ捕獲",
      "rawText": "36,300円 / 9月",
      "origin": "image19.jpeg / M21:P28",
      "imagePath": "docs/images/case_n19.jpg"
    },
    {
      "id": "case_n20",
      "caseGroup": "G_n20",
      "include": true,
      "month": "9月",
      "species": "スズメバチ",
      "location": "屋外（通気口）",
      "workType": "巣3つ／高所作業",
      "price": "77,000円",
      "duration": "",
      "area": "",
      "notes": "原文先頭部を採用。case_n11/n01と同C11",
      "visual": "軒下の通気口/格子場所にスズメバチ集団",
      "rawText": "巣3つ / 高所作業 / 77,000円 / 9月 / スズメバチ / 追加費用無し",
      "origin": "image20.jpeg / K20:M30",
      "imagePath": "docs/images/case_n20.jpg"
    },
    {
      "id": "case_n21",
      "caseGroup": "G_n20",
      "include": true,
      "month": "9月",
      "species": "スズメバチ",
      "location": "（屋根裏）",
      "workType": "高所作業",
      "price": "36,300円",
      "duration": "",
      "area": "",
      "notes": "case_n19と同案件と推定",
      "visual": "暗い空間（床下or屋根裏）に縦長の巣",
      "rawText": "36,300円",
      "origin": "image21.jpeg / P21:R30",
      "imagePath": "docs/images/case_n21.jpg"
    },
    {
      "id": "case_n22",
      "caseGroup": "C11",
      "include": true,
      "month": "9月",
      "species": "スズメバチ",
      "location": "軒下",
      "workType": "巣3つ／高所作業",
      "price": "77,000円",
      "duration": "",
      "area": "",
      "notes": "原文先頭部採用。case_n11案件C11",
      "visual": "軒下の梁にスズメバチの大きな球形巣",
      "rawText": "9月/スズメバチ/巣3つ/高所作業/77,000円 / 6月/アシナガバチ/高所作業/22,000円",
      "origin": "image22.jpeg / F17:I26",
      "imagePath": "docs/images/case_n22.jpg"
    },
    {
      "id": "case_n23",
      "caseGroup": "C15",
      "include": true,
      "month": "",
      "species": "スズメバチ",
      "location": "屋根裏",
      "workType": "屋根裏／高所作業",
      "price": "55,000円",
      "duration": "",
      "area": "",
      "notes": "画像はアシナガバチ似。要確認",
      "visual": "軒下にアシナガバチの大群（蜂の塊）",
      "rawText": "スズメバチ/屋根裏/高所作業/55,000円 / 7月/スズメバチ/高所作業/44,000円",
      "origin": "image23.jpeg / G28:J35",
      "imagePath": "docs/images/case_n23.jpg"
    },
    {
      "id": "case_n24",
      "caseGroup": "C9",
      "include": true,
      "month": "8月",
      "species": "スズメバチ",
      "location": "窓枠上",
      "workType": "高所作業",
      "price": "38,500円",
      "duration": "",
      "area": "",
      "notes": "Excel原文准拠",
      "visual": "窓枠の上にアシナガバチ（or小型スズメバチ）の小さな巣",
      "rawText": "8月 / スズメバチ / 高所作業 / 38,500円",
      "origin": "image24.jpeg / B38:D47",
      "imagePath": "docs/images/case_n24.jpg"
    },
    {
      "id": "case_n25",
      "caseGroup": "C8b",
      "include": true,
      "month": "7月",
      "species": "スズメバチ",
      "location": "屋内（タイル床）",
      "workType": "軽作業／捕獲",
      "price": "36,300円",
      "duration": "",
      "area": "",
      "notes": "case_n10とPAIR",
      "visual": "タイル床に粘着シート、捕獲済み蜂と巣の破片",
      "rawText": "（近接テキスト無し）",
      "origin": "image25.jpeg / T1:W8",
      "imagePath": "docs/images/case_n25.jpg"
    },
    {
      "id": "case_n26",
      "caseGroup": "C16",
      "include": true,
      "month": "",
      "species": "スズメバチ",
      "location": "雨樋の裏",
      "workType": "高所作業",
      "price": "",
      "duration": "",
      "area": "",
      "notes": "近接テキスト空。要確認",
      "visual": "雨樋の裏にスズメバチ大型巣（縦長）",
      "rawText": "（近接テキスト無し）",
      "origin": "image26.jpeg / B48:D58",
      "imagePath": "docs/images/case_n26.jpg"
    },
    {
      "id": "case_n27",
      "caseGroup": "C17",
      "include": true,
      "month": "",
      "species": "スズメバチ",
      "location": "屋根裏（梁）",
      "workType": "屋根裏／高所作業",
      "price": "",
      "duration": "",
      "area": "",
      "notes": "case_n29とPAIR推定",
      "visual": "屋根の梁裏に大型スズメバチ巣",
      "rawText": "（近接テキスト無し）",
      "origin": "image27.jpeg / N43:P53",
      "imagePath": "docs/images/case_n27.jpg"
    },
    {
      "id": "case_n28",
      "caseGroup": "C10",
      "include": true,
      "month": "8月",
      "species": "スズメバチ",
      "location": "屋根裏（撤去後）",
      "workType": "解体写真",
      "price": "55,000円",
      "duration": "",
      "area": "",
      "notes": "case_n18（C10）の撤去後解体写真",
      "visual": "大型スズメバチ巣の内部解体写真（セル構造、卵）",
      "rawText": "（近接テキスト無し）",
      "origin": "image28.jpeg / U32:W42",
      "imagePath": "docs/images/case_n28.jpg"
    },
    {
      "id": "case_n29",
      "caseGroup": "C17",
      "include": true,
      "month": "",
      "species": "スズメバチ",
      "location": "屋根（残蜂処理）",
      "workType": "粘着シート捕獲",
      "price": "",
      "duration": "",
      "area": "",
      "notes": "case_n27とPAIR推定",
      "visual": "屋根の梁に粘着シート、捕獲されたスズメバチ",
      "rawText": "（近接テキスト無し）",
      "origin": "image29.jpeg / P43:S51",
      "imagePath": "docs/images/case_n29.jpg"
    }
  ],
  "groups": [
    { "id": "C10",  "imageIds": ["case_n28"], "month": "9月", "species": "スズメバチ", "workType": "高所作業", "price": "44,000円", "include": true },
    { "id": "C11",  "imageIds": ["case_n22"], "month": "5月", "species": "スズメバチ", "workType": "高所作業", "price": "22,000円", "include": true },
    { "id": "C12",  "imageIds": ["case_n13","case_n14"], "month": "9月", "species": "オオスズメバチ", "workType": "地中", "price": "66,000円", "include": true },
    { "id": "C13",  "imageIds": ["case_n09"], "month": "6月", "species": "スズメバチ", "workType": "高所作業", "price": "38,500円", "include": true },
    { "id": "C15",  "imageIds": ["case_n23"], "month": "6月", "species": "アシナガバチ", "workType": "高所作業", "price": "22,000円", "include": true },
    { "id": "C16",  "imageIds": ["case_n26"], "month": "8月", "species": "スズメバチ", "workType": "高所作業", "price": "38,500円", "include": true },
    { "id": "C17",  "imageIds": ["case_n27","case_n29"], "month": "7月", "species": "スズメバチ", "workType": "高所作業", "price": "44,000円", "include": true },
    { "id": "C4",   "imageIds": ["case_n12"], "month": "", "species": "", "workType": "刺され跡（注意喚起）", "price": "", "include": true },
    { "id": "C5a",  "imageIds": ["case_n03","case_n04"], "month": "8月", "species": "スズメバチ", "workType": "床下", "price": "44,000円", "include": true },
    { "id": "C5b",  "imageIds": ["case_n05"], "month": "5月", "species": "アシナガバチ", "workType": "追加費用なし", "price": "11,000円", "include": true },
    { "id": "C5c",  "imageIds": ["case_n17"], "month": "7月", "species": "スズメバチ", "workType": "軽作業", "price": "36,300円", "include": true },
    { "id": "C7b",  "imageIds": ["case_n15","case_n16"], "month": "9月", "species": "スズメバチ", "workType": "追加費用なし", "price": "27,500円", "include": true },
    { "id": "C8",   "imageIds": ["case_n07","case_n08"], "month": "6月", "species": "スズメバチ", "workType": "高所作業", "price": "38,500円", "include": true },
    { "id": "C8b",  "imageIds": ["case_n10","case_n25"], "month": "7月", "species": "スズメバチ", "workType": "追加費用なし", "price": "33,000円", "include": true },
    { "id": "C9",   "imageIds": ["case_n24"], "month": "5月", "species": "スズメバチ", "workType": "高所作業", "price": "27,500円", "include": true },
    { "id": "G_n01","imageIds": ["case_n01","case_n11"], "month": "9月", "species": "スズメバチ", "location": "屋外", "workType": "追加費用なし", "price": "33,000円", "include": true },
    { "id": "G_n02","imageIds": ["case_n02","case_n06"], "month": "7月", "species": "オオスズメバチ", "workType": "高所作業", "price": "44,000円", "include": true },
    { "id": "G_n18","imageIds": ["case_n18"], "month": "9月", "species": "スズメバチ", "workType": "高所作業", "price": "77,000円", "notes": "巣3つ", "include": true },
    { "id": "G_n20","imageIds": ["case_n19","case_n20","case_n21"], "month": "8月", "species": "スズメバチ", "location": "屋根裏", "workType": "高所作業", "price": "55,000円", "include": true }
  ]
}
